Logger/__init__.py
Logger/cli.py
Logger/injector.py
Logger/log_generator_backup.py
Logger/logger_generator.py
Logger/prompts.py
Logger/utils.py
django_logger_cli-0.1.3.dist-info/LICENSE
django_logger_cli-0.1.3.dist-info/METADATA
django_logger_cli-0.1.3.dist-info/WHEEL
django_logger_cli-0.1.3.dist-info/entry_points.txt
django_logger_cli-0.1.3.dist-info/top_level.txt
django_logger_cli-0.1.3.dist-info/RECORD
