Metadata-Version: 2.1
Name: django-logger-cli
Version: 0.1.3
Summary: 🛠️ A CLI tool to generate Django-style logger configurations.
Home-page: https://github.com/codewithmanuu/django-logger
Author: Manukrishna S
Author-email: manukrishna.s2001@gmail.com
License: MIT
Project-URL: Documentation, https://github.com/codewithmanuu/django-logger#readme
Project-URL: Source, https://github.com/codewithmanuu/django-logger
Project-URL: Tracker, https://github.com/codewithmanuu/django-logger/issues
Classifier: Development Status :: 3 - Alpha
Classifier: Intended Audience :: Developers
Classifier: Topic :: Software Development :: Libraries :: Python Modules
Classifier: Environment :: Console
Classifier: Programming Language :: Python :: 3
Classifier: Programming Language :: Python :: 3.10
Classifier: License :: OSI Approved :: MIT License
Classifier: Operating System :: OS Independent
Requires-Python: >=3.7
License-File: LICENSE
Requires-Dist: click>=8.0
